dogfood_logger/__init__.py
dogfood_logger/logger.py
dogfood_logger/packageData/sampleData.dat
dogfood_logger_package-0.1.4.dist-info/LICENSE.txt
dogfood_logger_package-0.1.4.dist-info/METADATA
dogfood_logger_package-0.1.4.dist-info/WHEEL
dogfood_logger_package-0.1.4.dist-info/RECORD
