Metadata-Version: 2.1
Name: dogfood-logger-package
Version: 0.1.4
Summary: 
Author: Your Name
Author-email: you@example.com
Requires-Python: >=3.9,<4.0
Classifier: Programming Language :: Python :: 3
Classifier: Programming Language :: Python :: 3.9
Classifier: Programming Language :: Python :: 3.10
Classifier: Programming Language :: Python :: 3.11
Requires-Dist: pip-tools (>=6.13.0,<7.0.0)
Requires-Dist: setuptools (>=67.7.2,<68.0.0)
